calculator_2023_02_15/__init__.py
calculator_2023_02_15/calculator.py
calculator_2023_02_15-0.1.dist-info/LICENSE
calculator_2023_02_15-0.1.dist-info/METADATA
calculator_2023_02_15-0.1.dist-info/WHEEL
calculator_2023_02_15-0.1.dist-info/top_level.txt
calculator_2023_02_15-0.1.dist-info/RECORD
