Metadata-Version: 2.1
Name: calculator-2023-02-15
Version: 0.1
Summary: An extraordinarily basic calculator package
Author: Rapolas Strazdas
Author-email: rmstrazdas@outlook.com
Classifier: Programming Language :: Python :: 3
Classifier: License :: OSI Approved :: MIT License
Classifier: Operating System :: OS Independent
Requires-Python: >=3.6
License-File: LICENSE
